sdk/client.py
sdk/completion_choice.py
sdk/completion_collection.py
sdk/completion_deleted.py
sdk/completion_message.py
sdk/completion_message_assistant.py
sdk/completion_message_developer.py
sdk/completion_message_system.py
sdk/completion_message_tool.py
sdk/completion_message_user.py
sdk/completion_request.py
sdk/completion_response.py
sdk/completion_tokens_details.py
sdk/completion_usage.py
sdk/completions_tag.py
sdk/error.py
sdk/error_detail.py
sdk/error_exception.py
sdk/prompt_tokens_details.py
sdk/response_mcp_tool.py
sdk/response_prompt.py
sdk/response_reasoning.py
sdk/response_request.py
sdk/response_request_input.py
sdk/response_request_input_function_call.py
sdk/response_request_input_function_call_output.py
sdk/response_request_input_mcp_list_tools.py
sdk/response_request_input_message.py
sdk/response_request_text.py
sdk/response_request_text_format.py
sdk/response_request_text_format_json_schema.py
sdk/response_request_text_format_text.py
sdk/response_request_tool.py
sdk/response_request_tool_function.py
sdk/response_response.py
sdk/response_response_error.py
sdk/response_response_output.py
sdk/response_response_output_function_call.py
sdk/response_response_output_message.py
sdk/responses_tag.py
sdkfabric_openai-0.2.1.dist-info/licenses/LICENSE
sdkfabric_openai-0.2.1.dist-info/METADATA
sdkfabric_openai-0.2.1.dist-info/WHEEL
sdkfabric_openai-0.2.1.dist-info/top_level.txt
sdkfabric_openai-0.2.1.dist-info/RECORD
