Metadata-Version: 2.4
Name: sdkfabric-openai
Version: 0.2.1
Summary: Openai Python SDK managed by SDK Fabric
Author-email: Christoph Kappestein <christoph.kappestein@gmail.com>
License: MIT
Project-URL: Homepage, https://github.com/sdk-fabric/openai-python
Project-URL: Issues, https://github.com/sdk-fabric/openai-python/issues
Classifier: Programming Language :: Python :: 3
Classifier: License :: OSI Approved :: MIT License
Classifier: Operating System :: OS Independent
Classifier: Topic :: Software Development :: Code Generators
Requires-Python: >=3.8
License-File: LICENSE
Requires-Dist: sdkgen-client
Dynamic: license-file
